{
  "FacaReserva": [
    {
      "txtNome": "asdasd",
      "data": "",
      "textAreObs": "",
      "emailE-mail": "",
      "dateDataSaida": "",
      "numberAdultos": "",
      "numberCriancas": "",
      "id": 1
    },
    {
      "txtNome": "www",
      "data": "12323",
      "textAreObs": "",
      "emailE-mail": "",
      "dateDataSaida": "",
      "numberAdultos": "",
      "numberCriancas": "",
      "id": 2
    },
    {
      "txtNome": "ggg",
      "data": "",
      "textAreObs": "Perto da praia",
      "emailE-mail": "wwww@ssss.com",
      "dateDataSaida": "2005-01-21",
      "numberAdultos": "2",
      "numberCriancas": "3",
      "id": 3
    },
    {
      "txtNome": "ggg",
      "data": "3233-02-21",
      "textAreObs": "Perto da praia",
      "emailE-mail": "wwww@ssss.com",
      "dateDataSaida": "2005-01-21",
      "numberAdultos": "2",
      "numberCriancas": "3",
      "id": 4
    },
    {
      "txtNome": "sadasd",
      "data": "0213-03-21",
      "textAreObs": "sadas",
      "emailEmail": "sadasd@sadas",
      "dateDataSaida": "3233-02-12",
      "numberAdultos": "3",
      "numberCriancas": "3",
      "id": 5
    },
    {
      "txtNome": "sadasd",
      "data": "0213-03-21",
      "textAreObs": "sadas",
      "emailEmail": "sadasd@sadas",
      "dateDataSaida": "3233-02-12",
      "numberAdultos": "3",
      "numberCriancas": "3",
      "id": 6
    },
    {
      "txtNome": "sadasd",
      "data": "0213-03-21",
      "textAreObs": "sadas",
      "emailEmail": "sadasd@sadas",
      "dateDataSaida": "3233-02-12",
      "numberAdultos": "3",
      "numberCriancas": "3",
      "id": 7
    },
    {
      "txtNome": "sadasd",
      "data": "0213-03-21",
      "textAreObs": "sadas",
      "emailEmail": "sadasd@sadas",
      "dateDataSaida": "3233-02-12",
      "numberAdultos": "3",
      "numberCriancas": "3",
      "id": 8
    }
  ]
}